{
  "phase": "Phase 5 v7i",
  "title": "Full Phase 5 Canon Consolidation with Product-Module Frontier Separation",
  "status": "CANON_CONSOLIDATED_PRODUCT_MODULE_FRONTIER_SEPARATED_V8_READY_WITH_OPEN_FRONTIERS",
  "global_pass": true,
  "phase5_closed": false,
  "source_summaries_loaded": 7,
  "source_package_hashes_recorded": 13,
  "canon_layers": 9,
  "claim_dispositions": 7,
  "frontiers_separated": 5,
  "guardrail_checks": 8,
  "guardrail_checks_passed": 8,
  "max_loaded_numeric_residual": 1.152670228422045e-12,
  "residual_threshold": 1e-09,
  "canonical_carrier_statement": "single cyclic base N is retained as doubled orientation carrier Z/(2N)Z; product modules use products of doubled cyclic pieces with native pairwise coupling tensors",
  "product_module_statement": "supported for swept bounded native pairwise histories; complete arbitrary QBL history classification remains open",
  "next_target": "Phase 5 v8: Final Phase 5 Canon Package"
}